project1/luhn_corrected-20250103T090944Z-001/luhn_corrected/luhn_controller.v
/* 
Developed by : Vecha Sathwik
Date : 26 - Jan -2025
Description : This is the controller module for the Luhn algorithm. It controls the datapath module.
Rev : 0.1

*/



`timescale 1ns / 1ps
module luhn_controller (
    input clk,
    input rst,
    input go,
    input odd,
    input stop,
    output reg load_digit,
    output reg mult_sel,
    output reg load_sum,
    output reg output_enable,
    output reg count_enable,
    output reg sum_enable
);

// Parameterized states
parameter s0 = 4'b0000;
parameter s1 = 4'b0001;
parameter s2 = 4'b0010;
parameter s3 = 4'b0011;
parameter s4 = 4'b0100;
parameter s5 = 4'b0101;
parameter s6 = 4'b0110;
parameter s7 = 4'b0111;
parameter s8 = 4'b1000;
parameter s9 = 4'b1001;
parameter s10 = 4'b1010;

reg [3:0] next_state;
reg [3:0] present_state;

always @(posedge(clk) or posedge(rst)) begin
    if(rst) begin
        load_digit <= 1'b0;
        mult_sel <= 1'b0;
        load_sum <= 1'b0;
        output_enable <= 1'b0;
        count_enable <= 1'b0;
        sum_enable <= 1'b0;
        //present_state <= s0;
        //next_state <= s0;
    end
    else begin
      present_state <= next_state;
    end
end

always @(present_state or go) begin
    if (go == 1'b1 & present_state == s0) begin
        next_state = s1;
        load_digit = 1'b0;
        mult_sel = 1'b0;
        load_sum = 1'b0;
        output_enable = 1'b0;
        count_enable = 1'b0;
        sum_enable = 1'b0;              
    end
    else begin
        case (present_state)
            s1 : begin
                load_digit = 1'b1;
                mult_sel = 1'b0;
                load_sum = 1'b0;
                output_enable = 1'b0;
                count_enable = 1'b0;
                next_state = s2;
            end 
            s2 : begin
                next_state = s3;
                //load_digit = 1'b1;
            end
            s3 : begin
                if (odd == 1'b0) begin
                    next_state = s4;
                end
                else begin
                    next_state = s5;
                end
            end
            s4 : begin
                load_digit = 1'b0;
                output_enable = 1'b0;
                mult_sel = 1'b1;
                count_enable = 1'b1;
                next_state = s6;
            end
            s5 : begin
                load_digit = 1'b0;
                output_enable = 1'b0;
                mult_sel = 1'b0;
                count_enable = 1'b1;
                next_state = s6;
            end
            s6 : begin
                load_digit = 1'b0;
                mult_sel = 1'bz;
                output_enable = 1'b0;
                count_enable = 1'b0;
                next_state = s7;
            end
            s7 : begin
                sum_enable = 1'b1;
                next_state = stop ? s9 : s8;                
            end
            s8 : begin
                sum_enable = 1'b0;
                next_state = s1;
            end
            s9 : begin
                output_enable = 1'b1;
                next_state = s0;
            end
            default: next_state = s0;
        endcase
    end
end

endmodule

project1/luhn_corrected-20250103T090944Z-001/luhn_corrected/luhn_datapath.v
/* 
Developed by : Vecha Sathwik
Date : 26 - Jan -2025
Description : This is the datapath module for the Luhn algorithm. It performs the necessary operations to validate the card number.
Rev : 0.1

*/



`timescale 1ns / 1ps
module luhn_datapath (
    input clk,
    input rst,
    input [3:0] serial_in,
    input load_digit,
    input mult_sel,
    //input load_mult,
    input load_sum,
    input output_enable,
    input count_enable,
    input sum_enable,
    output reg validate,
    output reg odd,
    output reg go,
    output reg stop
);

reg [4:0] count;
reg [3:0] value_out;
reg [4:0] mult_out;
reg [4:0] mult_value_out;
reg [4:0] comp_value_zero;
reg [4:0] comp_value_one;
reg [4:0] comp_out;
reg [10:0] sum;


// Memory to store card digits
reg [3:0] card_number [15:0];
integer j;
integer k;

// Resetting the card number and sum
always @(posedge rst) begin
    for (j = 0; j < 16; j = j + 1) begin
        card_number[j] = 4'b0;
    end
    j = 0;
    sum = 10'b0;
end

// Storing the card number
always @(posedge clk) begin
    if (serial_in !== 4'bx && serial_in !== 4'bz && j <= 15) begin
        card_number[j] <= serial_in;
        j <= j + 1;
        //$display("Card Number[%0d]: %0d", j, serial_in); //For debugging
    end
    if (j == 16 & stop == 1'b0) begin
        go <= 1'b1;
    end else begin
        go <= 1'b0;
    end
end


//Registers or Sequential Logic
always @(posedge(rst) or posedge(clk)) begin
    if(rst == 1'b1) begin
        count <= 5'b0000;
        k <= 0;
        stop <= 1'b0;
        //validate <= 1'b0;
    end
    else begin
        if(load_digit == 1'b1) begin
            value_out <= card_number[k];
        end
        else if (mult_sel == 1'b1) begin
            mult_out <= mult_value_out;
        end
        else if (mult_sel == 1'b0) begin
            mult_out <= value_out;
        end
        
        else if (mult_out > 9) begin
            comp_out <= comp_value_one;
        end
        else begin
            comp_out <= comp_value_zero;
        end
        
    end
end

//Combinational Logic
always @(*) begin
    mult_value_out = value_out *2;
    comp_value_one = mult_out - 9;
    comp_value_zero = mult_out;
    if(sum_enable == 1'b1) begin
        sum = sum + comp_out;
        k = k + 1;
    end
end




//Counter Logic
always @(posedge(clk)) begin
    if(count_enable == 1'b1 & rst == 1'b0) begin
        count <= count + 1'b1;
    end
    if (count[0] == 1'b1) begin
        odd <= 1'b1;
    end
    else begin
        odd <= 1'b0;
    end
end

//Output Logic
always @(count) begin
    if (count == 5'b10000) begin
        stop = 1'b1;
    end
    else begin
        stop = 1'b0;
    end
end

//Output Logic
always @(posedge(clk)) begin
    if (sum%10 == 1'b0 & stop == 1'b1) begin
        validate <= 1'b1;
    end
    else begin
        validate <= 1'b0;
    end
end

endmodule

project1/luhn_corrected-20250103T090944Z-001/luhn_corrected/luhn_topmodule_cd.v
/* 
Developed by : Vecha Sathwik
Date : 26 - Jan -2025
Description : This is the top module for the Luhn algorithm. It instantiates the datapath and controller modules and connects them. 
Version : Beta
Rev : 0.1

*/



`timescale 1ns / 1ps
`include "luhn_datapath.v"
`include "luhn_controller.v"

module luhn_topmodule_cd (
    input clk,
    input rst,
    input [3:0] serial_in,
    output validate
);

wire go;
wire odd;
wire stop;
wire load_digit;
wire mult_sel;
wire load_sum;
wire output_enable;
wire count_enable;
wire sum_enable;


luhn_datapath luhn_datapath_inst (
    .clk(clk),
    .rst(rst),
    .serial_in(serial_in),
    .load_digit(load_digit),
    .mult_sel(mult_sel),
    .load_sum(load_sum),
    .output_enable(output_enable),
    .count_enable(count_enable),
    .sum_enable(sum_enable),
    .validate(validate),
    .odd(odd),
    .go(go),
    .stop(stop)
);

luhn_controller luhn_controller_inst (
    .clk(clk),
    .rst(rst),
    .go(go),
    .odd(odd),
    .load_digit(load_digit),
    .mult_sel(mult_sel),
    .load_sum(load_sum),
    .output_enable(output_enable),
    .count_enable(count_enable),
    .sum_enable(sum_enable),
    .stop(stop)
);
    
endmodule

project1/luhn_corrected-20250103T090944Z-001/luhn_corrected/luhn_testbench.v
/*
Testbench for Luhn Algorithm Validation.
*/
`include "luhn_topmodule_cd.v"
`timescale 1ns/1ps
module luhn_testbench;

    reg clk;
    reg rst;
    reg [3:0] serial_in;
    wire validate;
    
    // Instantiate top module
    luhn_topmodule_cd uut (
        .clk(clk),
        .rst(rst),
        .serial_in(serial_in),
        .validate(validate)
    );

    // Clock generation
    initial begin
        clk = 0;
        forever #5 clk = ~clk;
    end

    // Test vector
    reg [63:0] card_number = 64'h5334670022992784; // Example valid card number
    integer i;

    initial begin
        $dumpfile("luhn_testbench.vcd");
        $dumpvars;
        // Reset system
        rst = 1;
        #10;
        rst = 0;

        // Send card number digits serially
        for (i = 15; i >= 0; i = i - 1) begin
            serial_in = card_number[4 * i +: 4];
            #10;
        end

        // Wait for validation
        #1500;
        

        // Check results
        /*if (uut.datapath.validate) begin
            $display("Card is valid.");
        end else begin
            $display("Card is invalid.");
        end*/

        $finish;
    end

endmodule

project1/luhn_corrected-20250103T090944Z-001/luhn_corrected/luhn_testbench.vcd
$date
	Tue Jan 28 12:19:18 2025
$end
$version
	Icarus Verilog
$end
$timescale
	1ps
$end
$scope module luhn_testbench $end
$var wire 1 ! validate $end
$var reg 64 " card_number [63:0] $end
$var reg 1 # clk $end
$var reg 1 $ rst $end
$var reg 4 % serial_in [3:0] $end
$var integer 32 & i [31:0] $end
$scope module uut $end
$var wire 1 # clk $end
$var wire 1 $ rst $end
$var wire 4 ' serial_in [3:0] $end
$var wire 1 ! validate $end
$var wire 1 ( sum_enable $end
$var wire 1 ) stop $end
$var wire 1 * output_enable $end
$var wire 1 + odd $end
$var wire 1 , mult_sel $end
$var wire 1 - load_sum $end
$var wire 1 . load_digit $end
$var wire 1 / go $end
$var wire 1 0 count_enable $end
$scope module luhn_controller_inst $end
$var wire 1 # clk $end
$var wire 1 $ rst $end
$var wire 1 ) stop $end
$var wire 1 + odd $end
$var wire 1 / go $end
$var parameter 4 1 s0 $end
$var parameter 4 2 s1 $end
$var parameter 4 3 s10 $end
$var parameter 4 4 s2 $end
$var parameter 4 5 s3 $end
$var parameter 4 6 s4 $end
$var parameter 4 7 s5 $end
$var parameter 4 8 s6 $end
$var parameter 4 9 s7 $end
$var parameter 4 : s8 $end
$var parameter 4 ; s9 $end
$var reg 1 0 count_enable $end
$var reg 1 . load_digit $end
$var reg 1 - load_sum $end
$var reg 1 , mult_sel $end
$var reg 4 < next_state [3:0] $end
$var reg 1 * output_enable $end
$var reg 4 = present_state [3:0] $end
$var reg 1 ( sum_enable $end
$upscope $end
$scope module luhn_datapath_inst $end
$var wire 1 # clk $end
$var wire 1 0 count_enable $end
$var wire 1 . load_digit $end
$var wire 1 - load_sum $end
$var wire 1 , mult_sel $end
$var wire 1 * output_enable $end
$var wire 1 $ rst $end
$var wire 4 > serial_in [3:0] $end
$var wire 1 ( sum_enable $end
$var reg 5 ? comp_out [4:0] $end
$var reg 5 @ comp_value_one [4:0] $end
$var reg 5 A comp_value_zero [4:0] $end
$var reg 5 B count [4:0] $end
$var reg 1 / go $end
$var reg 5 C mult_out [4:0] $end
$var reg 5 D mult_value_out [4:0] $end
$var reg 1 + odd $end
$var reg 1 ) stop $end
$var reg 11 E sum [10:0] $end
$var reg 1 ! validate $end
$var reg 4 F value_out [3:0] $end
$var integer 32 G j [31:0] $end
$var integer 32 H k [31:0] $end
$upscope $end
$upscope $end
$upscope $end
$enddefinitions $end
$comment Show the parameter values. $end
$dumpall
b1001 ;
b1000 :
b111 9
b110 8
b101 7
b100 6
b11 5
b10 4
b1010 3
b1 2
b0 1
$end
#0
$dumpvars
b0 H
b0 G
bx F
b0 E
bx D
bx C
b0 B
bx A
bx @
bx ?
bx >
bx =
bx <
00
x/
0.
0-
0,
x+
0*
0)
0(
bx '
bx &
bx %
1$
0#
b101001100110100011001110000000000100010100110010010011110000100 "
x!
$end
#5000
b0 <
0/
0+
0!
1#
#10000
0#
b101 %
b101 '
b101 >
b1111 &
0$
#15000
b0xxxx A
b0xxxx C
b0 =
b1 G
1#
#20000
0#
b11 %
b11 '
b11 >
b1110 &
#25000
b10 G
1#
#30000
0#
b1101 &
#35000
b11 G
1#
#40000
0#
b100 %
b100 '
b100 >
b1100 &
#45000
b100 G
1#
#50000
0#
b110 %
b110 '
b110 >
b1011 &
#55000
b101 G
1#
#60000
0#
b111 %
b111 '
b111 >
b1010 &
#65000
b110 G
1#
#70000
0#
b0 %
b0 '
b0 >
b1001 &
#75000
b111 G
1#
#80000
0#
b1000 &
#85000
b1000 G
1#
#90000
0#
b10 %
b10 '
b10 >
b111 &
#95000
b1001 G
1#
#100000
0#
b110 &
#105000
b1010 G
1#
#110000
0#
b1001 %
b1001 '
b1001 >
b101 &
#115000
b1011 G
1#
#120000
0#
b100 &
#125000
b1100 G
1#
#130000
0#
b10 %
b10 '
b10 >
b11 &
#135000
b1101 G
1#
#140000
0#
b111 %
b111 '
b111 >
b10 &
#145000
b1110 G
1#
#150000
0#
b1000 %
b1000 '
b1000 >
b1 &
#155000
b1111 G
1#
#160000
0#
b100 %
b100 '
b100 >
b0 &
#165000
b10000 G
1#
#170000
0#
b11111111111111111111111111111111 &
#175000
b1 <
1/
1#
#180000
0#
#185000
b10 <
1.
b1 =
1#
#190000
0#
#195000
b1010 D
b11 <
b101 F
b10 =
1#
#200000
0#
#205000
b100 <
b11 =
1#
#210000
0#
#215000
b110 <
10
1,
0.
b100 =
1#
#220000
0#
#225000
b111 <
00
z,
b1010 A
b1 @
b110 =
b1010 C
b1 B
1#
#230000
0#
#235000
b1 H
b1 E
b1000 <
1(
b1 ?
b111 =
1+
1#
#240000
0#
#245000
b1 <
0(
b1000 =
1#
#250000
0#
#255000
b10 <
0,
1.
b1 =
1#
#260000
0#
#265000
b11 <
b110 D
b10 =
b11 F
1#
#270000
0#
#275000
b101 <
b11 =
1#
#280000
0#
#285000
b110 <
10
0.
b101 =
1#
#290000
0#
#295000
b11 A
b11010 @
b111 <
00
z,
b11 C
b110 =
b10 B
1#
#300000
0#
#305000
b10 H
b100 E
b1000 <
1(
b111 =
b11 ?
0+
1#
#310000
0#
#315000
b1 <
0(
b1000 =
1#
#320000
0#
#325000
b10 <
0,
1.
b1 =
1#
#330000
0#
#335000
b11 <
b10 =
1#
#340000
0#
#345000
b100 <
b11 =
1#
#350000
0#
#355000
b110 <
10
1,
0.
b100 =
1#
#360000
0#
#365000
b111 <
00
z,
b110 A
b11101 @
b110 =
b110 C
b11 B
1#
#370000
0#
#375000
b11 H
b1010 E
b1000 <
1(
b110 ?
b111 =
1+
1#
#380000
0#
#385000
b1 <
0(
b1000 =
1#
#390000
0#
#395000
b10 <
0,
1.
b1 =
1#
#400000
0#
#405000
b11 <
b1000 D
b10 =
b100 F
1#
#410000
0#
#415000
b101 <
b11 =
1#
#420000
0#
#425000
b110 <
10
0.
b101 =
1#
#430000
0#
#435000
b100 A
b11011 @
b111 <
00
z,
b100 C
b110 =
b100 B
1#
#440000
0#
#445000
b100 H
b1110 E
b1000 <
1(
b111 =
b100 ?
0+
1#
#450000
0#
#455000
b1 <
0(
b1000 =
1#
#460000
0#
#465000
b10 <
0,
1.
b1 =
1#
#470000
0#
#475000
b1100 D
b11 <
b110 F
b10 =
1#
#480000
0#
#485000
b100 <
b11 =
1#
#490000
0#
#495000
b110 <
10
1,
0.
b100 =
1#
#500000
0#
#505000
b111 <
00
z,
b1100 A
b11 @
b110 =
b1100 C
b101 B
1#
#510000
0#
#515000
b101 H
b10001 E
b1000 <
1(
b11 ?
b111 =
1+
1#
#520000
0#
#525000
b1 <
0(
b1000 =
1#
#530000
0#
#535000
b10 <
0,
1.
b1 =
1#
#540000
0#
#545000
b11 <
b1110 D
b10 =
b111 F
1#
#550000
0#
#555000
b101 <
b11 =
1#
#560000
0#
#565000
b110 <
10
0.
b101 =
1#
#570000
0#
#575000
b111 A
b11110 @
b111 <
00
z,
b111 C
b110 =
b110 B
1#
#580000
0#
#585000
b110 H
b11000 E
b1000 <
1(
b111 =
b111 ?
0+
1#
#590000
0#
#595000
b1 <
0(
b1000 =
1#
#600000
0#
#605000
b10 <
0,
1.
b1 =
1#
#610000
0#
#615000
b0 D
b11 <
b0 F
b10 =
1#
#620000
0#
#625000
b100 <
b11 =
1#
#630000
0#
#635000
b110 <
10
1,
0.
b100 =
1#
#640000
0#
#645000
b111 <
00
z,
b0 A
b10111 @
b110 =
b0 C
b111 B
1#
#650000
0#
#655000
b111 H
b1000 <
1(
b0 ?
b111 =
1+
1#
#660000
0#
#665000
b1 <
0(
b1000 =
1#
#670000
0#
#675000
b10 <
0,
1.
b1 =
1#
#680000
0#
#685000
b11 <
b10 =
1#
#690000
0#
#695000
b101 <
b11 =
1#
#700000
0#
#705000
b110 <
10
0.
b101 =
1#
#710000
0#
#715000
b111 <
00
z,
b110 =
b1000 B
1#
#720000
0#
#725000
b1000 H
b1000 <
1(
b111 =
0+
1#
#730000
0#
#735000
b1 <
0(
b1000 =
1#
#740000
0#
#745000
b10 <
0,
1.
b1 =
1#
#750000
0#
#755000
b100 D
b11 <
b10 F
b10 =
1#
#760000
0#
#765000
b100 <
b11 =
1#
#770000
0#
#775000
b110 <
10
1,
0.
b100 =
1#
#780000
0#
#785000
b111 <
00
z,
b100 A
b11011 @
b110 =
b100 C
b1001 B
1#
#790000
0#
#795000
b1001 H
b11100 E
b1000 <
1(
b100 ?
b111 =
1+
1#
#800000
0#
#805000
b1 <
0(
b1000 =
1#
#810000
0#
#815000
b10 <
0,
1.
b1 =
1#
#820000
0#
#825000
b11 <
b10 =
1#
#830000
0#
#835000
b101 <
b11 =
1#
#840000
0#
#845000
b110 <
10
0.
b101 =
1#
#850000
0#
#855000
b10 A
b11001 @
b111 <
00
z,
b10 C
b110 =
b1010 B
1#
#860000
0#
#865000
b1010 H
b11110 E
b1000 <
1(
b111 =
b10 ?
0+
1#
#870000
0#
#875000
b1 <
0(
b1000 =
1#
#880000
0#
#885000
b10 <
0,
1.
b1 =
1#
#890000
0#
#895000
b10010 D
b11 <
b1001 F
b10 =
1#
#900000
0#
#905000
b100 <
b11 =
1#
#910000
0#
#915000
b110 <
10
1,
0.
b100 =
1#
#920000
0#
#925000
b111 <
00
z,
b10010 A
b1001 @
b110 =
b10010 C
b1011 B
1#
#930000
0#
#935000
b1011 H
b100111 E
b1000 <
1(
b1001 ?
b111 =
1+
1#
#940000
0#
#945000
b1 <
0(
b1000 =
1#
#950000
0#
#955000
b10 <
0,
1.
b1 =
1#
#960000
0#
#965000
b11 <
b10 =
1#
#970000
0#
#975000
b101 <
b11 =
1#
#980000
0#
#985000
b110 <
10
0.
b101 =
1#
#990000
0#
#995000
b1001 A
b0 @
b111 <
00
z,
b1001 C
b110 =
b1100 B
1#
#1000000
0#
#1005000
b1100 H
b110000 E
b1000 <
1(
b111 =
0+
1#
#1010000
0#
#1015000
b1 <
0(
b1000 =
1#
#1020000
0#
#1025000
b10 <
0,
1.
b1 =
1#
#1030000
0#
#1035000
b100 D
b11 <
b10 F
b10 =
1#
#1040000
0#
#1045000
b100 <
b11 =
1#
#1050000
0#
#1055000
b110 <
10
1,
0.
b100 =
1#
#1060000
0#
#1065000
b111 <
00
z,
b100 A
b11011 @
b110 =
b100 C
b1101 B
1#
#1070000
0#
#1075000
b1101 H
b110100 E
b1000 <
1(
b100 ?
b111 =
1+
1#
#1080000
0#
#1085000
b1 <
0(
b1000 =
1#
#1090000
0#
#1095000
b10 <
0,
1.
b1 =
1#
#1100000
0#
#1105000
b11 <
b1110 D
b10 =
b111 F
1#
#1110000
0#
#1115000
b101 <
b11 =
1#
#1120000
0#
#1125000
b110 <
10
0.
b101 =
1#
#1130000
0#
#1135000
b111 A
b11110 @
b111 <
00
z,
b111 C
b110 =
b1110 B
1#
#1140000
0#
#1145000
b1110 H
b111011 E
b1000 <
1(
b111 =
b111 ?
0+
1#
#1150000
0#
#1155000
b1 <
0(
b1000 =
1#
#1160000
0#
#1165000
b10 <
0,
1.
b1 =
1#
#1170000
0#
#1175000
b10000 D
b11 <
b1000 F
b10 =
1#
#1180000
0#
#1185000
b100 <
b11 =
1#
#1190000
0#
#1195000
b110 <
10
1,
0.
b100 =
1#
#1200000
0#
#1205000
b111 <
00
z,
b10000 A
b111 @
b110 =
b10000 C
b1111 B
1#
#1210000
0#
#1215000
b1111 H
b1000010 E
b1000 <
1(
b111 =
1+
1#
#1220000
0#
#1225000
b1 <
0(
b1000 =
1#
#1230000
0#
#1235000
b10 <
0,
1.
b1 =
1#
#1240000
0#
#1245000
b11 <
b1000 D
b10 =
b100 F
1#
#1250000
0#
#1255000
b101 <
b11 =
1#
#1260000
0#
#1265000
b110 <
10
0.
b101 =
1#
#1270000
0#
#1275000
b100 A
b11011 @
b111 <
00
z,
1)
b100 C
b110 =
b10000 B
1#
#1280000
0#
#1285000
b10000 H
b1000110 E
b1001 <
1(
b111 =
b100 ?
0/
0+
1#
#1290000
0#
#1295000
b0 <
1*
b1001 =
1!
1#
#1300000
0#
#1305000
b0 =
1#
